README.md
setup.py
qimen/hello.py
qimen.egg-info/PKG-INFO
qimen.egg-info/SOURCES.txt
qimen.egg-info/dependency_links.txt
qimen.egg-info/top_level.txt