Metadata-Version: 1.0
Name: qimen
Version: 0.1.0
Summary: Qimen Natural Language Processing
Home-page: https://github.com/ownthink/Qimen
Author: Yener(Zheng Wenyu)
Author-email: help@ownthink.com
License: MIT
Platform: UNKNOWN
